Metadata-Version: 2.1
Name: gauss-binomial-probability
Version: 1.5
Summary: Gaussian and Binomial distributions
Home-page: UNKNOWN
Author: Jainish Shah
Author-email: jainishnikul2525@gmail.com
License: UNKNOWN
Platform: UNKNOWN
